flask_session/__init__.py
flask_session/sessions.py
Flask_Session_Refresh_Option-0.1.2.dist-info/LICENSE
Flask_Session_Refresh_Option-0.1.2.dist-info/METADATA
Flask_Session_Refresh_Option-0.1.2.dist-info/WHEEL
Flask_Session_Refresh_Option-0.1.2.dist-info/top_level.txt
Flask_Session_Refresh_Option-0.1.2.dist-info/RECORD
