Metadata-Version: 2.1
Name: Flask-Session-Refresh-Option
Version: 0.1.2
Summary: Adds server-side session support to your Flask application
Home-page: https://github.com/luismigsantana/flask-session-not-refresh-option
Author: Luis Miguel Santana
Author-email: miguelsantanna.ms@gmail.com
License: BSD
Platform: any
Classifier: Environment :: Web Environment
Classifier: Intended Audience :: Developers
Classifier: License :: OSI Approved :: BSD License
Classifier: Operating System :: OS Independent
Classifier: Programming Language :: Python :: 2
Classifier: Topic :: Internet :: WWW/HTTP :: Dynamic Content
Classifier: Topic :: Software Development :: Libraries :: Python Modules
License-File: LICENSE
Requires-Dist: Flask (>=0.8)
Requires-Dist: cachelib
